{"type": "scene", "properties": {"baseExtent": {"cx": 114.51506806938342, "cy": 22.624325623427936, "width": 2.5464353488601716, "height": 2.5464353488601716, "rotation": 0}, "origin": {"x": 114.51506806938342, "y": 22.624325623427936, "z": 0.0}, "zScale": 0.0001, "light": "directional"}, "layers": [{"type": "layer", "id": 0, "properties": {"name": "\u041a\u0438\u0442\u0430\u0439", "clickable": true, "visible": true, "type": "point", "objType": "Cylinder", "propertyNames": ["ID", "NAME", "X", "Y", "HEIGHT_B", "HEIGHT_A", "a"]}, "data": {"materials": [{"type": 0, "c": 9993655}], "blocks": [{"url": "./data/index/a0.json", "featureCount": 8}]}}, {"type": "layer", "id": 3, "properties": {"name": "\u0438\u0442\u043e\u0433", "clickable": true, "visible": true, "type": "dem", "clipped": false, "mtlNames": ["map (canvas)"], "mtlIdx": 0}, "data": [{"type": "block", "layer": 3, "block": 0, "materials": [{"type": 0, "image": {"url": "./data/index/b0.png"}, "ds": 1, "bm": true, "mtlIndex": 0, "useNow": true}]}, {"type": "block", "layer": 3, "block": 0, "width": 2.5464353488601716, "height": 2.5464353488601716, "translate": [0.0, 0.0, 0], "zScale": 0.0001, "grid": {"width": 201, "height": 201, "url": "./data/index/b0.bin"}}]}]}